lab 6/D_flipflop.vhdl
library ieee;
use ieee.std_logic_1164.all;
use ieee.numeric_std.all;
entity D_flipflop is
port
(
d,clk:in std_logic;
a:out std_logic:='0';
abar:out std_logic:='1'
);
end D_flipflop;
architecture s of D_flipflop is
begin
ha:process(d,clk)
begin
if (rising_edge(clk)) then
if d='1' then
a<='1';
abar<='0';
else
a<='0';
abar<='1';
end if;
end if;
end process ha;
end s;

lab 6/D_flipflop_tb.vhdl
library ieee;
use ieee.std_logic_1164.all;
use ieee.numeric_std.all;
entity D_flipflop_tb is
end D_flipflop_tb;
architecture s of D_flipflop_tb is
component D_flipflop
port
(
d,clk:in std_logic;
a,abar:out std_logic
);
end component;
signal d,clk,a,abar: std_logic;
begin
ha: D_flipflop port map (d,clk,a,abar);
process begin
clk<='0';
d<='1';
wait for 1 ns;
clk<='1';
d<='1';
wait for 1 ns;
clk<='0';
d<='0';
wait for 1 ns;
clk<='1';
d<='0';
wait for 1 ns;
end process;
end s;

lab 6/D_flipflop.vcd
$date
  Tue Jun 06 21:53:12 2023
$end
$version
  GHDL v0
$end
$timescale
  1 fs
$end
$scope module standard $end
$upscope $end
$scope module std_logic_1164 $end
$upscope $end
$scope module numeric_std $end
$upscope $end
$scope module d_flipflop_tb $end
$var reg 1 ! d $end
$var reg 1 " clk $end
$var reg 1 # a $end
$var reg 1 $ abar $end
$scope module ha $end
$var reg 1 % d $end
$var reg 1 & clk $end
$var reg 1 ' a $end
$var reg 1 ( abar $end
$upscope $end
$upscope $end
$enddefinitions $end
#0
1!
0"
0#
1$
1%
0&
0'
1(
#1000000
1"
1#
0$
1&
1'
0(
#2000000
0!
0"
0%
0&
#3000000
1"
0#
1$
1&
0'
1(
#4000000
1!
0"
1%
0&
#5000000
1"
1#
0$
1&
1'
0(
#6000000
0!
0"
0%
0&
#7000000
1"
0#
1$
1&
0'
1(
#8000000
1!
0"
1%
0&
#9000000
1"
1#
0$
1&
1'
0(
#10000000
0!
0"
0%
0&
#11000000
1"
0#
1$
1&
0'
1(
#12000000
1!
0"
1%
0&
#13000000
1"
1#
0$
1&
1'
0(
#14000000
0!
0"
0%
0&
#15000000
1"
0#
1$
1&
0'
1(
#16000000
1!
0"
1%
0&
#17000000
1"
1#
0$
1&
1'
0(
#18000000
0!
0"
0%
0&
#19000000
1"
0#
1$
1&
0'
1(
#20000000
1!
0"
1%
0&
#21000000
1"
1#
0$
1&
1'
0(
#22000000
0!
0"
0%
0&
#23000000
1"
0#
1$
1&
0'
1(
#24000000
1!
0"
1%
0&
#25000000
1"
1#
0$
1&
1'
0(
#26000000
0!
0"
0%
0&
#27000000
1"
0#
1$
1&
0'
1(
#28000000
1!
0"
1%
0&
#29000000
1"
1#
0$
1&
1'
0(
#30000000
0!
0"
0%
0&
#31000000
1"
0#
1$
1&
0'
1(
#32000000
1!
0"
1%
0&
#33000000
1"
1#
0$
1&
1'
0(
#34000000
0!
0"
0%
0&
#35000000
1"
0#
1$
1&
0'
1(
#36000000
1!
0"
1%
0&
#37000000
1"
1#
0$
1&
1'
0(
#38000000
0!
0"
0%
0&
#39000000
1"
0#
1$
1&
0'
1(
#40000000
1!
0"
1%
0&
#41000000
1"
1#
0$
1&
1'
0(
#42000000
0!
0"
0%
0&
#43000000
1"
0#
1$
1&
0'
1(
#44000000
1!
0"
1%
0&
#45000000
1"
1#
0$
1&
1'
0(
#46000000
0!
0"
0%
0&
#47000000
1"
0#
1$
1&
0'
1(
#48000000
1!
0"
1%
0&
#49000000
1"
1#
0$
1&
1'
0(
#50000000
0!
0"
0%
0&
#51000000
1"
0#
1$
1&
0'
1(
#52000000
1!
0"
1%
0&
#53000000
1"
1#
0$
1&
1'
0(
#54000000
0!
0"
0%
0&
#55000000
1"
0#
1$
1&
0'
1(
#56000000
1!
0"
1%
0&
#57000000
1"
1#
0$
1&
1'
0(
#58000000
0!
0"
0%
0&
#59000000
1"
0#
1$
1&
0'
1(
#60000000
1!
0"
1%
0&
#61000000
1"
1#
0$
1&
1'
0(
#62000000
0!
0"
0%
0&
#63000000
1"
0#
1$
1&
0'
1(
#64000000
1!
0"
1%
0&
#65000000
1"
1#
0$
1&
1'
0(
#66000000
0!
0"
0%
0&
#67000000
1"
0#
1$
1&
0'
1(
#68000000
1!
0"
1%
0&
#69000000
1"
1#
0$
1&
1'
0(
#70000000
0!
0"
0%
0&
#71000000
1"
0#
1$
1&
0'
1(
#72000000
1!
0"
1%
0&
#73000000
1"
1#
0$
1&
1'
0(
#74000000
0!
0"
0%
0&
#75000000
1"
0#
1$
1&
0'
1(
#76000000
1!
0"
1%
0&
#77000000
1"
1#
0$
1&
1'
0(
#78000000
0!
0"
0%
0&
#79000000
1"
0#
1$
1&
0'
1(
#80000000
1!
0"
1%
0&
#81000000
1"
1#
0$
1&
1'
0(
#82000000
0!
0"
0%
0&
#83000000
1"
0#
1$
1&
0'
1(
#84000000
1!
0"
1%
0&
#85000000
1"
1#
0$
1&
1'
0(
#86000000
0!
0"
0%
0&
#87000000
1"
0#
1$
1&
0'
1(
#88000000
1!
0"
1%
0&
#89000000
1"
1#
0$
1&
1'
0(
#90000000
0!
0"
0%
0&
#91000000
1"
0#
1$
1&
0'
1(
#92000000
1!
0"
1%
0&
#93000000
1"
1#
0$
1&
1'
0(
#94000000
0!
0"
0%
0&
#95000000
1"
0#
1$
1&
0'
1(
#96000000
1!
0"
1%
0&
#97000000
1"
1#
0$
1&
1'
0(
#98000000
0!
0"
0%
0&
#99000000
1"
0#
1$
1&
0'
1(
#100000000
1!
0"
1%
0&
#101000000
1"
1#
0$
1&
1'
0(
#102000000
0!
0"
0%
0&
#103000000
1"
0#
1$
1&
0'
1(
#104000000
1!
0"
1%
0&
#105000000
1"
1#
0$
1&
1'
0(
#106000000
0!
0"
0%
0&
#107000000
1"
0#
1$
1&
0'
1(
#108000000
1!
0"
1%
0&
#109000000
1"
1#
0$
1&
1'
0(
#110000000
0!
0"
0%
0&
#111000000
1"
0#
1$
1&
0'
1(
#112000000
1!
0"
1%
0&
#113000000
1"
1#
0$
1&
1'
0(
#114000000
0!
0"
0%
0&
#115000000
1"
0#
1$
1&
0'
1(
#116000000
1!
0"
1%
0&
#117000000
1"
1#
0$
1&
1'
0(
#118000000
0!
0"
0%
0&
#119000000
1"
0#
1$
1&
0'
1(
#120000000
1!
0"
1%
0&
#121000000
1"
1#
0$
1&
1'
0(
#122000000
0!
0"
0%
0&
#123000000
1"
0#
1$
1&
0'
1(
#124000000
1!
0"
1%
0&
#125000000
1"
1#
0$
1&
1'
0(
#126000000
0!
0"
0%
0&
#127000000
1"
0#
1$
1&
0'
1(
#128000000
1!
0"
1%
0&
#129000000
1"
1#
0$
1&
1'
0(
#130000000
0!
0"
0%
0&
#131000000
1"
0#
1$
1&
0'
1(
#132000000
1!
0"
1%
0&
#133000000
1"
1#
0$
1&
1'
0(
#134000000
0!
0"
0%
0&
#135000000
1"
0#
1$
1&
0'
1(
#136000000
1!
0"
1%
0&
#137000000
1"
1#
0$
1&
1'
0(
#138000000
0!
0"
0%
0&
#139000000
1"
0#
1$
1&
0'
1(
#140000000
1!
0"
1%
0&
#141000000
1"
1#
0$
1&
1'
0(
#142000000
0!
0"
0%
0&
#143000000
1"
0#
1$
1&
0'
1(
#144000000
1!
0"
1%
0&
#145000000
1"
1#
0$
1&
1'
0(
#146000000
0!
0"
0%
0&
#147000000
1"
0#
1$
1&
0'
1(
#148000000
1!
0"
1%
0&
#149000000
1"
1#
0$
1&
1'
0(
#150000000
0!
0"
0%
0&
#151000000
1"
0#
1$
1&
0'
1(
#152000000
1!
0"
1%
0&
#153000000
1"
1#
0$
1&
1'
0(
#154000000
0!
0"
0%
0&
#155000000
1"
0#
1$
1&
0'
1(
#156000000
1!
0"
1%
0&
#157000000
1"
1#
0$
1&
1'
0(
#158000000
0!
0"
0%
0&
#159000000
1"
0#
1$
1&
0'
1(
#160000000
1!
0"
1%
0&
#161000000
1"
1#
0$
1&
1'
0(
#162000000
0!
0"
0%
0&
#163000000
1"
0#
1$
1&
0'
1(
#164000000
1!
0"
1%
0&
#165000000
1"
1#
0$
1&
1'
0(
#166000000
0!
0"
0%
0&
#167000000
1"
0#
1$
1&
0'
1(
#168000000
1!
0"
1%
0&
#169000000
1"
1#
0$
1&
1'
0(
#170000000
0!
0"
0%
0&
#171000000
1"
0#
1$
1&
0'
1(
#172000000
1!
0"
1%
0&
#173000000
1"
1#
0$
1&
1'
0(
#174000000
0!
0"
0%
0&
#175000000
1"
0#
1$
1&
0'
1(
#176000000
1!
0"
1%
0&
#177000000
1"
1#
0$
1&
1'
0(
#178000000
0!
0"
0%
0&
#179000000
1"
0#
1$
1&
0'
1(
#180000000
1!
0"
1%
0&
#181000000
1"
1#
0$
1&
1'
0(
#182000000
0!
0"
0%
0&
#183000000
1"
0#
1$
1&
0'
1(
#184000000
1!
0"
1%
0&
#185000000
1"
1#
0$
1&
1'
0(
#186000000
0!
0"
0%
0&
#187000000
1"
0#
1$
1&
0'
1(
#188000000
1!
0"
1%
0&
#189000000
1"
1#
0$
1&
1'
0(
#190000000
0!
0"
0%
0&
#191000000
1"
0#
1$
1&
0'
1(
#192000000
1!
0"
1%
0&
#193000000
1"
1#
0$
1&
1'
0(
#194000000
0!
0"
0%
0&
#195000000
1"
0#
1$
1&
0'
1(
#196000000
1!
0"
1%
0&
#197000000
1"
1#
0$
1&
1'
0(
#198000000
0!
0"
0%
0&
#199000000
1"
0#
1$
1&
0'
1(
#200000000
1!
0"
1%
0&
#201000000
1"
1#
0$
1&
1'
0(
#202000000
0!
0"
0%
0&
#203000000
1"
0#
1$
1&
0'
1(
#204000000
1!
0"
1%
0&
#205000000
1"
1#
0$
1&
1'
0(
#206000000
0!
0"
0%
0&
#207000000
1"
0#
1$
1&
0'
1(
#208000000
1!
0"
1%
0&
#209000000
1"
1#
0$
1&
1'
0(
#210000000
0!
0"
0%
0&
#211000000
1"
0#
1$
1&
0'
1(
#212000000
1!
0"
1%
0&
#213000000
1"
1#
0$
1&
1'
0(
#214000000
0!
0"
0%
0&
#215000000
1"
0#
1$
1&
0'
1(
#216000000
1!
0"
1%
0&
#217000000
1"
1#
0$
1&
1'
0(
#218000000
0!
0"
0%
0&
#219000000
1"
0#
1$
1&
0'
1(
#220000000
1!
0"
1%
0&
#221000000
1"
1#
0$
1&
1'
0(
#222000000
0!
0"
0%
0&
#223000000
1"
0#
1$
1&
0'
1(
#224000000
1!
0"
1%
0&
#225000000
1"
1#
0$
1&
1'
0(
#226000000
0!
0"
0%
0&
#227000000
1"
0#
1$
1&
0'
1(
#228000000
1!
0"
1%
0&
#229000000
1"
1#
0$
1&
1'
0(
#230000000
0!
0"
0%
0&
#231000000
1"
0#
1$
1&
0'
1(
#232000000
1!
0"
1%
0&
#233000000
1"
1#
0$
1&
1'
0(
#234000000
0!
0"
0%
0&
#235000000
1"
0#
1$
1&
0'
1(
#236000000
1!
0"
1%
0&
#237000000
1"
1#
0$
1&
1'
0(
#238000000
0!
0"
0%
0&
#239000000
1"
0#
1$
1&
0'
1(
#240000000
1!
0"
1%
0&
#241000000
1"
1#
0$
1&
1'
0(
#242000000
0!
0"
0%
0&
#243000000
1"
0#
1$
1&
0'
1(
#244000000
1!
0"
1%
0&
#245000000
1"
1#
0$
1&
1'
0(
#246000000
0!
0"
0%
0&
#247000000
1"
0#
1$
1&
0'
1(
#248000000
1!
0"
1%
0&
#249000000
1"
1#
0$
1&
1'
0(
#250000000
0!
0"
0%
0&
#251000000
1"
0#
1$
1&
0'
1(
#252000000
1!
0"
1%
0&
#253000000
1"
1#
0$
1&
1'
0(
#254000000
0!
0"
0%
0&
#255000000
1"
0#
1$
1&
0'
1(
#256000000
1!
0"
1%
0&
#257000000
1"
1#
0$
1&
1'
0(
#258000000
0!
0"
0%
0&
#259000000
1"
0#
1$
1&
0'
1(
#260000000
1!
0"
1%
0&
#261000000
1"
1#
0$
1&
1'
0(
#262000000
0!
0"
0%
0&
#263000000
1"
0#
1$
1&
0'
1(
#264000000
1!
0"
1%
0&
#265000000
1"
1#
0$
1&
1'
0(
#266000000
0!
0"
0%
0&
#267000000
1"
0#
1$
1&
0'
1(
#268000000
1!
0"
1%
0&
#269000000
1"
1#
0$
1&
1'
0(
#270000000
0!
0"
0%
0&
#271000000
1"
0#
1$
1&
0'
1(
#272000000
1!
0"
1%
0&
#273000000
1"
1#
0$
1&
1'
0(
#274000000
0!
0"
0%
0&
#275000000
1"
0#
1$
1&
0'
1(
#276000000
1!
0"
1%
0&
#277000000
1"
1#
0$
1&
1'
0(
#278000000
0!
0"
0%
0&
#279000000
1"
0#
1$
1&
0'
1(
#280000000
1!
0"
1%
0&
#281000000
1"
1#
0$
1&
1'
0(
#282000000
0!
0"
0%
0&
#283000000
1"
0#
1$
1&
0'
1(
#284000000
1!
0"
1%
0&
#285000000
1"
1#
0$
1&
1'
0(
#286000000
0!
0"
0%
0&
#287000000
1"
0#
1$
1&
0'
1(
#288000000
1!
0"
1%
0&
#289000000
1"
1#
0$
1&
1'
0(
#290000000
0!
0"
0%
0&
#291000000
1"
0#
1$
1&
0'
1(
#292000000
1!
0"
1%
0&
#293000000
1"
1#
0$
1&
1'
0(
#294000000
0!
0"
0%
0&
#295000000
1"
0#
1$
1&
0'
1(
#296000000
1!
0"
1%
0&
#297000000
1"
1#
0$
1&
1'
0(
#298000000
0!
0"
0%
0&
#299000000
1"
0#
1$
1&
0'
1(
#300000000
1!
0"
1%
0&
#301000000
1"
1#
0$
1&
1'
0(
#302000000
0!
0"
0%
0&
#303000000
1"
0#
1$
1&
0'
1(
#304000000
1!
0"
1%
0&
#305000000
1"
1#
0$
1&
1'
0(
#306000000
0!
0"
0%
0&
#307000000
1"
0#
1$
1&
0'
1(
#308000000
1!
0"
1%
0&
#309000000
1"
1#
0$
1&
1'
0(
#310000000
0!
0"
0%
0&
#311000000
1"
0#
1$
1&
0'
1(
#312000000
1!
0"
1%
0&
#313000000
1"
1#
0$
1&
1'
0(
#314000000
0!
0"
0%
0&
#315000000
1"
0#
1$
1&
0'
1(
#316000000
1!
0"
1%
0&
#317000000
1"
1#
0$
1&
1'
0(
#318000000
0!
0"
0%
0&
#319000000
1"
0#
1$
1&
0'
1(
#320000000
1!
0"
1%
0&
#321000000
1"
1#
0$
1&
1'
0(
#322000000
0!
0"
0%
0&
#323000000
1"
0#
1$
1&
0'
1(
#324000000
1!
0"
1%
0&
#325000000
1"
1#
0$
1&
1'
0(
#326000000
0!
0"
0%
0&
#327000000
1"
0#
1$
1&
0'
1(
#328000000
1!
0"
1%
0&
#329000000
1"
1#
0$
1&
1'
0(
#330000000
0!
0"
0%
0&
#331000000
1"
0#
1$
1&
0'
1(
#332000000
1!
0"
1%
0&
#333000000
1"
1#
0$
1&
1'
0(
#334000000
0!
0"
0%
0&
#335000000
1"
0#
1$
1&
0'
1(
#336000000
1!
0"
1%
0&
#337000000
1"
1#
0$
1&
1'
0(
#338000000
0!
0"
0%
0&
#339000000
1"
0#
1$
1&
0'
1(
#340000000
1!
0"
1%
0&
#341000000
1"
1#
0$
1&
1'
0(
#342000000
0!
0"
0%
0&
#343000000
1"
0#
1$
1&
0'
1(
#344000000
1!
0"
1%
0&
#345000000
1"
1#
0$
1&
1'
0(
#346000000
0!
0"
0%
0&
#347000000
1"
0#
1$
1&
0'
1(
#348000000
1!
0"
1%
0&
#349000000
1"
1#
0$
1&
1'
0(
#350000000
0!
0"
0%
0&
#351000000
1"
0#
1$
1&
0'
1(
#352000000
1!
0"
1%
0&
#353000000
1"
1#
0$
1&
1'
0(
#354000000
0!
0"
0%
0&
#355000000
1"
0#
1$
1&
0'
1(
#356000000
1!
0"
1%
0&
#357000000
1"
1#
0$
1&
1'
0(
#358000000
0!
0"
0%
0&
#359000000
1"
0#
1$
1&
0'
1(
#360000000
1!
0"
1%
0&
#361000000
1"
1#
0$
1&
1'
0(
#362000000
0!
0"
0%
0&
#363000000
1"
0#
1$
1&
0'
1(
#364000000
1!
0"
1%
0&
#365000000
1"
1#
0$
1&
1'
0(
#366000000
0!
0"
0%
0&
#367000000
1"
0#
1$
1&
0'
1(
#368000000
1!
0"
1%
0&
#369000000
1"
1#
0$
1&
1'
0(
#370000000
0!
0"
0%
0&
#371000000
1"
0#
1$
1&
0'
1(
#372000000
1!
0"
1%
0&
#373000000
1"
1#
0$
1&
1'
0(
#374000000
0!
0"
0%
0&
#375000000
1"
0#
1$
1&
0'
1(
#376000000
1!
0"
1%
0&
#377000000
1"
1#
0$
1&
1'
0(
#378000000
0!
0"
0%
0&
#379000000
1"
0#
1$
1&
0'
1(
#380000000
1!
0"
1%
0&
#381000000
1"
1#
0$
1&
1'
0(
#382000000
0!
0"
0%
0&
#383000000
1"
0#
1$
1&
0'
1(
#384000000
1!
0"
1%
0&
#385000000
1"
1#
0$
1&
1'
0(
#386000000
0!
0"
0%
0&
#387000000
1"
0#
1$
1&
0'
1(
#388000000
1!
0"
1%
0&
#389000000
1"
1#
0$
1&
1'
0(
#390000000
0!
0"
0%
0&
#391000000
1"
0#
1$
1&
0'
1(
#392000000
1!
0"
1%
0&
#393000000
1"
1#
0$
1&
1'
0(
#394000000
0!
0"
0%
0&
#395000000
1"
0#
1$
1&
0'
1(
#396000000
1!
0"
1%
0&
#397000000
1"
1#
0$
1&
1'
0(
#398000000
0!
0"
0%
0&
#399000000
1"
0#
1$
1&
0'
1(
#400000000
1!
0"
1%
0&
#401000000
1"
1#
0$
1&
1'
0(
#402000000
0!
0"
0%
0&
#403000000
1"
0#
1$
1&
0'
1(
#404000000
1!
0"
1%
0&
#405000000
1"
1#
0$
1&
1'
0(
#406000000
0!
0"
0%
0&
#407000000
1"
0#
1$
1&
0'
1(
#408000000
1!
0"
1%
0&
#409000000
1"
1#
0$
1&
1'
0(
#410000000
0!
0"
0%
0&
#411000000
1"
0#
1$
1&
0'
1(
#412000000
1!
0"
1%
0&
#413000000
1"
1#
0$
1&
1'
0(
#414000000
0!
0"
0%
0&
#415000000
1"
0#
1$
1&
0'
1(
#416000000
1!
0"
1%
0&
#417000000
1"
1#
0$
1&
1'
0(
#418000000
0!
0"
0%
0&
#419000000
1"
0#
1$
1&
0'
1(
#420000000
1!
0"
1%
0&
#421000000
1"
1#
0$
1&
1'
0(
#422000000
0!
0"
0%
0&
#423000000
1"
0#
1$
1&
0'
1(
#424000000
1!
0"
1%
0&
#425000000
1"
1#
0$
1&
1'
0(
#426000000
0!
0"
0%
0&
#427000000
1"
0#
1$
1&
0'
1(
#428000000
1!
0"
1%
0&
#429000000
1"
1#
0$
1&
1'
0(
#430000000
0!
0"
0%
0&
#431000000
1"
0#
1$
1&
0'
1(
#432000000
1!
0"
1%
0&
#433000000
1"
1#
0$
1&
1'
0(
#434000000
0!
0"
0%
0&
#435000000
1"
0#
1$
1&
0'
1(
#436000000
1!
0"
1%
0&
#437000000
1"
1#
0$
1&
1'
0(
#438000000
0!
0"
0%
0&
#439000000
1"
0#
1$
1&
0'
1(
#440000000
1!
0"
1%
0&
#441000000
1"
1#
0$
1&
1'
0(
#442000000
0!
0"
0%
0&
#443000000
1"
0#
1$
1&
0'
1(
#444000000
1!
0"
1%
0&
#445000000
1"
1#
0$
1&
1'
0(
#446000000
0!
0"
0%
0&
#447000000
1"
0#
1$
1&
0'
1(
#448000000
1!
0"
1%
0&
#449000000
1"
1#
0$
1&
1'
0(
#450000000
0!
0"
0%
0&
#451000000
1"
0#
1$
1&
0'
1(
#452000000
1!
0"
1%
0&
#453000000
1"
1#
0$
1&
1'
0(
#454000000
0!
0"
0%
0&
#455000000
1"
0#
1$
1&
0'
1(
#456000000
1!
0"
1%
0&
#457000000
1"
1#
0$
1&
1'
0(
#458000000
0!
0"
0%
0&
#459000000
1"
0#
1$
1&
0'
1(
#460000000
1!
0"
1%
0&
#461000000
1"
1#
0$
1&
1'
0(
#462000000
0!
0"
0%
0&
#463000000
1"
0#
1$
1&
0'
1(
#464000000
1!
0"
1%
0&
#465000000
1"
1#
0$
1&
1'
0(
#466000000
0!
0"
0%
0&
#467000000
1"
0#
1$
1&
0'
1(
#468000000
1!
0"
1%
0&
#469000000
1"
1#
0$
1&
1'
0(
#470000000
0!
0"
0%
0&
#471000000
1"
0#
1$
1&
0'
1(
#472000000
1!
0"
1%
0&
#473000000
1"
1#
0$
1&
1'
0(
#474000000
0!
0"
0%
0&
#475000000
1"
0#
1$
1&
0'
1(
#476000000
1!
0"
1%
0&
#477000000
1"
1#
0$
1&
1'
0(
#478000000
0!
0"
0%
0&
#479000000
1"
0#
1$
1&
0'
1(
#480000000
1!
0"
1%
0&
#481000000
1"
1#
0$
1&
1'
0(
#482000000
0!
0"
0%
0&
#483000000
1"
0#
1$
1&
0'
1(
#484000000
1!
0"
1%
0&
#485000000
1"
1#
0$
1&
1'
0(
#486000000
0!
0"
0%
0&
#487000000
1"
0#
1$
1&
0'
1(
#488000000
1!
0"
1%
0&
#489000000
1"
1#
0$
1&
1'
0(
#490000000
0!
0"
0%
0&
#491000000
1"
0#
1$
1&
0'
1(
#492000000
1!
0"
1%
0&
#493000000
1"
1#
0$
1&
1'
0(
#494000000
0!
0"
0%
0&
#495000000
1"
0#
1$
1&
0'
1(
#496000000
1!
0"
1%
0&
#497000000
1"
1#
0$
1&
1'
0(
#498000000
0!
0"
0%
0&
#499000000
1"
0#
1$
1&
0'
1(
#500000000
1!
0"
1%
0&
#501000000
1"
1#
0$
1&
1'
0(
#502000000
0!
0"
0%
0&
#503000000
1"
0#
1$
1&
0'
1(
#504000000
1!
0"
1%
0&
#505000000
1"
1#
0$
1&
1'
0(
#506000000
0!
0"
0%
0&
#507000000
1"
0#
1$
1&
0'
1(
#508000000
1!
0"
1%
0&
#509000000
1"
1#
0$
1&
1'
0(
#510000000
0!
0"
0%
0&
#511000000
1"
0#
1$
1&
0'
1(
#512000000
1!
0"
1%
0&
#513000000
1"
1#
0$
1&
1'
0(
#514000000
0!
0"
0%
0&
#515000000
1"
0#
1$
1&
0'
1(
#516000000
1!
0"
1%
0&
#517000000
1"
1#
0$
1&
1'
0(
#518000000
0!
0"
0%
0&
#519000000
1"
0#
1$
1&
0'
1(
#520000000
1!
0"
1%
0&
#521000000
1"
1#
0$
1&
1'
0(
#522000000
0!
0"
0%
0&
#523000000
1"
0#
1$
1&
0'
1(
#524000000
1!
0"
1%
0&
#525000000
1"
1#
0$
1&
1'
0(
#526000000
0!
0"
0%
0&
#527000000
1"
0#
1$
1&
0'
1(
#528000000
1!
0"
1%
0&
#529000000
1"
1#
0$
1&
1'
0(
#530000000
0!
0"
0%
0&
#531000000
1"
0#
1$
1&
0'
1(
#532000000
1!
0"
1%
0&
#533000000
1"
1#
0$
1&
1'
0(
#534000000
0!
0"
0%
0&
#535000000
1"
0#
1$
1&
0'
1(
#536000000
1!
0"
1%
0&
#537000000
1"
1#
0$
1&
1'
0(
#538000000
0!
0"
0%
0&
#539000000
1"
0#
1$
1&
0'
1(
#540000000
1!
0"
1%
0&
#541000000
1"
1#
0$
1&
1'
0(
#542000000
0!
0"
0%
0&
#543000000
1"
0#
1$
1&
0'
1(
#544000000
1!
0"
1%
0&
#545000000
1"
1#
0$
1&
1'
0(
#546000000
0!
0"
0%
0&
#547000000
1"
0#
1$
1&
0'
1(
#548000000
1!
0"
1%
0&
#549000000
1"
1#
0$
1&
1'
0(
#550000000
0!
0"
0%
0&
#551000000
1"
0#
1$
1&
0'
1(
#552000000
1!
0"
1%
0&
#553000000
1"
1#
0$
1&
1'
0(
#554000000
0!
0"
0%
0&
#555000000
1"
0#
1$
1&
0'
1(
#556000000
1!
0"
1%
0&
#557000000
1"
1#
0$
1&
1'
0(
#558000000
0!
0"
0%
0&
#559000000
1"
0#
1$
1&
0'
1(
#560000000
1!
0"
1%
0&
#561000000
1"
1#
0$
1&
1'
0(
#562000000
0!
0"
0%
0&
#563000000
1"
0#
1$
1&
0'
1(
#564000000
1!
0"
1%
0&
#565000000
1"
1#
0$
1&
1'
0(
#566000000
0!
0"
0%
0&
#567000000
1"
0#
1$
1&
0'
1(
#568000000
1!
0"
1%
0&
#569000000
1"
1#
0$
1&
1'
0(
#570000000
0!
0"
0%
0&
#571000000
1"
0#
1$
1&
0'
1(
#572000000
1!
0"
1%
0&
#573000000
1"
1#
0$
1&
1'
0(
#574000000
0!
0"
0%
0&
#575000000
1"
0#
1$
1&
0'
1(
#576000000
1!
0"
1%
0&
#577000000
1"
1#
0$
1&
1'
0(
#578000000
0!
0"
0%
0&
#579000000
1"
0#
1$
1&
0'
1(
#580000000
1!
0"
1%
0&
#581000000
1"
1#
0$
1&
1'
0(
#582000000
0!
0"
0%
0&
#583000000
1"
0#
1$
1&
0'
1(
#584000000
1!
0"
1%
0&
#585000000
1"
1#
0$
1&
1'
0(
#586000000
0!
0"
0%
0&
#587000000
1"
0#
1$
1&
0'
1(
#588000000
1!
0"
1%
0&
#589000000
1"
1#
0$
1&
1'
0(
#590000000
0!
0"
0%
0&
#591000000
1"
0#
1$
1&
0'
1(
#592000000
1!
0"
1%
0&
#593000000
1"
1#
0$
1&
1'
0(
#594000000
0!
0"
0%
0&
#595000000
1"
0#
1$
1&
0'
1(
#596000000
1!
0"
1%
0&
#597000000
1"
1#
0$
1&
1'
0(
#598000000
0!
0"
0%
0&
#599000000
1"
0#
1$
1&
0'
1(
#600000000
1!
0"
1%
0&
#601000000
1"
1#
0$
1&
1'
0(
#602000000
0!
0"
0%
0&
#603000000
1"
0#
1$
1&
0'
1(
#604000000
1!
0"
1%
0&
#605000000
1"
1#
0$
1&
1'
0(
#606000000
0!
0"
0%
0&
#607000000
1"
0#
1$
1&
0'
1(
#608000000
1!
0"
1%
0&
#609000000
1"
1#
0$
1&
1'
0(
#610000000
0!
0"
0%
0&
#611000000
1"
0#
1$
1&
0'
1(
#612000000
1!
0"
1%
0&
#613000000
1"
1#
0$
1&
1'
0(
#614000000
0!
0"
0%
0&
#615000000
1"
0#
1$
1&
0'
1(
#616000000
1!
0"
1%
0&
#617000000
1"
1#
0$
1&
1'
0(
#618000000
0!
0"
0%
0&
#619000000
1"
0#
1$
1&
0'
1(
#620000000
1!
0"
1%
0&
#621000000
1"
1#
0$
1&
1'
0(
#622000000
0!
0"
0%
0&
#623000000
1"
0#
1$
1&
0'
1(
#624000000
1!
0"
1%
0&
#625000000
1"
1#
0$
1&
1'
0(
#626000000
0!
0"
0%
0&
#627000000
1"
0#
1$
1&
0'
1(
#628000000
1!
0"
1%
0&
#629000000
1"
1#
0$
1&
1'
0(
#630000000
0!
0"
0%
0&
#631000000
1"
0#
1$
1&
0'
1(
#632000000
1!
0"
1%
0&
#633000000
1"
1#
0$
1&
1'
0(
#634000000
0!
0"
0%
0&
#635000000
1"
0#
1$
1&
0'
1(
#636000000
1!
0"
1%
0&
#637000000
1"
1#
0$
1&
1'
0(
#638000000
0!
0"
0%
0&
#639000000
1"
0#
1$
1&
0'
1(
#640000000
1!
0"
1%
0&
#641000000
1"
1#
0$
1&
1'
0(
#642000000
0!
0"
0%
0&
#643000000
1"
0#
1$
1&
0'
1(
#644000000
1!
0"
1%
0&
#645000000
1"
1#
0$
1&
1'
0(
#646000000
0!
0"
0%
0&
#647000000
1"
0#
1$
1&
0'
1(
#648000000
1!
0"
1%
0&
#649000000
1"
1#
0$
1&
1'
0(
#650000000
0!
0"
0%
0&
#651000000
1"
0#
1$
1&
0'
1(
#652000000
1!
0"
1%
0&
#653000000
1"
1#
0$
1&
1'
0(
#654000000
0!
0"
0%
0&
#655000000
1"
0#
1$
1&
0'
1(
#656000000
1!
0"
1%
0&
#657000000
1"
1#
0$
1&
1'
0(
#658000000
0!
0"
0%
0&
#659000000
1"
0#
1$
1&
0'
1(
#660000000
1!
0"
1%
0&
#661000000
1"
1#
0$
1&
1'
0(
#662000000
0!
0"
0%
0&
#663000000
1"
0#
1$
1&
0'
1(
#664000000
1!
0"
1%
0&
#665000000
1"
1#
0$
1&
1'
0(
#666000000
0!
0"
0%
0&
#667000000
1"
0#
1$
1&
0'
1(
#668000000
1!
0"
1%
0&
#669000000
1"
1#
0$
1&
1'
0(
#670000000
0!
0"
0%
0&
#671000000
1"
0#
1$
1&
0'
1(
#672000000
1!
0"
1%
0&
#673000000
1"
1#
0$
1&
1'
0(
#674000000
0!
0"
0%
0&
#675000000
1"
0#
1$
1&
0'
1(
#676000000
1!
0"
1%
0&
#677000000
1"
1#
0$
1&
1'
0(
#678000000
0!
0"
0%
0&
#679000000
1"
0#
1$
1&
0'
1(
#680000000
1!
0"
1%
0&
#681000000
1"
1#
0$
1&
1'
0(
#682000000
0!
0"
0%
0&
#683000000
1"
0#
1$
1&
0'
1(
#684000000
1!
0"
1%
0&
#685000000
1"
1#
0$
1&
1'
0(
#686000000
0!
0"
0%
0&
#687000000
1"
0#
1$
1&
0'
1(
#688000000
1!
0"
1%
0&
#689000000
1"
1#
0$
1&
1'
0(
#690000000
0!
0"
0%
0&
#691000000
1"
0#
1$
1&
0'
1(
#692000000
1!
0"
1%
0&
#693000000
1"
1#
0$
1&
1'
0(
#694000000
0!
0"
0%
0&
#695000000
1"
0#
1$
1&
0'
1(
#696000000
1!
0"
1%
0&
#697000000
1"
1#
0$
1&
1'
0(
#698000000
0!
0"
0%
0&
#699000000
1"
0#
1$
1&
0'
1(
#700000000
1!
0"
1%
0&
#701000000
1"
1#
0$
1&
1'
0(
#702000000
0!
0"
0%
0&
#703000000
1"
0#
1$
1&
0'
1(
#704000000
1!
0"
1%
0&
#705000000
1"
1#
0$
1&
1'
0(
#706000000
0!
0"
0%
0&
#707000000
1"
0#
1$
1&
0'
1(
#708000000
1!
0"
1%
0&
#709000000
1"
1#
0$
1&
1'
0(
